dmlx/__init__.py
dmlx/component.py
dmlx/context.py
dmlx/docs.py
dmlx/experiment.py
dmlx/property.py
dmlx-0.2.0.dist-info/WHEEL
dmlx-0.2.0.dist-info/METADATA
dmlx-0.2.0.dist-info/RECORD
