Metadata-Version: 2.4
Name: dmlx
Version: 0.2.0
Summary: Declarative machine learning experiments.
Keywords: declarative,machine learning,experiment,component,parameter,argument,option,management,command line interface,cli
Author: 3h
License-Expression: ISC
Requires-Dist: click>=8.2.1
Requires-Python: >=3.10
Project-URL: Changelog, https://github.com/huang2002/dmlx/blob/main/CHANGELOG.md
Project-URL: Documentation, https://github.com/huang2002/dmlx/blob/main/README.md
Project-URL: Homepage, https://github.com/huang2002/dmlx
Project-URL: Repository, https://github.com/huang2002/dmlx.git
